<?xml version="1.0" encoding="UTF-8"?>
<osm version="0.6" generator="Overpass API">
<note>The data included in this document is from www.openstreetmap.org. The data is made available under ODbL.</note>
<meta osm_base="2014-09-21T23:51:02Z"/>

  <way id="16401573">
    <nd ref="169284400"/>
    <nd ref="169284404"/>
    <nd ref="169284407"/>
    <nd ref="169284410"/>
    <nd ref="169284412"/>
    <nd ref="169284414"/>
    <nd ref="169284415"/>
    <nd ref="169284416"/>
    <tag k="access" v="private"/>
    <tag k="highway" v="service"/>
    <tag k="tiger:cfcc" v="A74"/>
    <tag k="tiger:county" v="Ashe, NC"/>
    <tag k="tiger:reviewed" v="no"/>
    <tag k="tiger:source" v="tiger_import_dch_v0.6_20070829"/>
    <tag k="tiger:tlid" v="154054934:154054936:154054938:154054939"/>
    <tag k="tiger:upload_uuid" v="bulk_upload.pl-f5d30e1e-b9c9-4043-8bc2-575d31645af6"/>
  </way>
  <way id="16414738">
    <nd ref="169430395"/>
    <nd ref="169430397"/>
    <nd ref="169430400"/>
    <nd ref="169430403"/>
    <nd ref="169430406"/>
    <nd ref="169430410"/>
    <nd ref="169430415"/>
    <nd ref="169430419"/>
    <nd ref="169430421"/>
    <nd ref="169430422"/>
    <nd ref="169430425"/>
    <nd ref="169430427"/>
    <nd ref="169430430"/>
    <nd ref="169430433"/>
    <nd ref="169430436"/>
    <nd ref="169430438"/>
    <nd ref="169430440"/>
    <nd ref="169430441"/>
    <nd ref="169430442"/>
    <nd ref="169430445"/>
    <nd ref="169430448"/>
    <nd ref="169430452"/>
    <nd ref="169430453"/>
    <nd ref="169430454"/>
    <nd ref="169430455"/>
    <nd ref="169430457"/>
    <nd ref="169430463"/>
    <nd ref="169430465"/>
    <nd ref="169430468"/>
    <nd ref="169430470"/>
    <nd ref="169430471"/>
    <nd ref="169430473"/>
    <nd ref="169430475"/>
    <nd ref="169430476"/>
    <nd ref="169430480"/>
    <nd ref="169430488"/>
    <nd ref="169430494"/>
    <nd ref="169430499"/>
    <nd ref="169430503"/>
    <nd ref="169430511"/>
    <nd ref="169430512"/>
    <nd ref="169430515"/>
    <nd ref="169430517"/>
    <nd ref="169284400"/>
    <nd ref="169430521"/>
    <nd ref="169430525"/>
    <nd ref="169430528"/>
    <nd ref="169430532"/>
    <nd ref="169430535"/>
    <nd ref="169430538"/>
    <nd ref="169430540"/>
    <nd ref="169430543"/>
    <nd ref="169430546"/>
    <nd ref="169430553"/>
    <nd ref="169430559"/>
    <nd ref="169430564"/>
    <nd ref="169430569"/>
    <nd ref="169430572"/>
    <nd ref="169430575"/>
    <nd ref="169430578"/>
    <nd ref="169430581"/>
    <nd ref="169430586"/>
    <nd ref="169430588"/>
    <nd ref="169430591"/>
    <nd ref="169430595"/>
    <nd ref="169430597"/>
    <nd ref="169430602"/>
    <nd ref="169430606"/>
    <nd ref="169430608"/>
    <nd ref="169430612"/>
    <nd ref="169430615"/>
    <nd ref="169430617"/>
    <nd ref="169430622"/>
    <nd ref="169430627"/>
    <nd ref="169430631"/>
    <nd ref="169430634"/>
    <nd ref="169430639"/>
    <nd ref="169430643"/>
    <nd ref="169430647"/>
    <nd ref="169430650"/>
    <nd ref="169430653"/>
    <nd ref="169430655"/>
    <nd ref="169430657"/>
    <nd ref="169430662"/>
    <nd ref="169430665"/>
    <nd ref="169430669"/>
    <nd ref="169430671"/>
    <nd ref="169430674"/>
    <nd ref="169430677"/>
    <nd ref="169430680"/>
    <nd ref="169430683"/>
    <nd ref="169430689"/>
    <nd ref="169430694"/>
    <nd ref="169430699"/>
    <nd ref="169430703"/>
    <nd ref="169430706"/>
    <nd ref="169430709"/>
    <nd ref="169430713"/>
    <nd ref="169430715"/>
    <nd ref="169430718"/>
    <nd ref="169430720"/>
    <nd ref="169430722"/>
    <nd ref="169430725"/>
    <nd ref="169430730"/>
    <nd ref="169430735"/>
    <nd ref="169430738"/>
    <nd ref="169430740"/>
    <nd ref="169430743"/>
    <nd ref="169276978"/>
    <nd ref="169430746"/>
    <nd ref="169430748"/>
    <nd ref="169430752"/>
    <nd ref="169430754"/>
    <nd ref="169430757"/>
    <nd ref="169430759"/>
    <nd ref="169430762"/>
    <nd ref="169430764"/>
    <nd ref="169430767"/>
    <nd ref="169430769"/>
    <nd ref="169430772"/>
    <nd ref="169430774"/>
    <nd ref="169430777"/>
    <nd ref="169430780"/>
    <nd ref="169430782"/>
    <nd ref="169430784"/>
    <nd ref="169430787"/>
    <nd ref="169430790"/>
    <nd ref="169430792"/>
    <nd ref="169430796"/>
    <nd ref="169430799"/>
    <nd ref="169430802"/>
    <nd ref="169430804"/>
    <nd ref="169430809"/>
    <nd ref="169430813"/>
    <nd ref="169430816"/>
    <nd ref="169430820"/>
    <nd ref="169276911"/>
    <nd ref="169430824"/>
    <nd ref="169430826"/>
    <nd ref="169430829"/>
    <nd ref="169430834"/>
    <nd ref="169430836"/>
    <nd ref="169430839"/>
    <nd ref="169430842"/>
    <nd ref="169430849"/>
    <nd ref="169430854"/>
    <nd ref="169430857"/>
    <nd ref="169430863"/>
    <nd ref="169430868"/>
    <nd ref="169430872"/>
    <nd ref="169430878"/>
    <nd ref="169430882"/>
    <nd ref="169430885"/>
    <nd ref="169430888"/>
    <nd ref="169430891"/>
    <nd ref="169430894"/>
    <nd ref="169430897"/>
    <nd ref="169430901"/>
    <nd ref="169430903"/>
    <nd ref="169430905"/>
    <nd ref="169430907"/>
    <nd ref="169430908"/>
    <nd ref="169430912"/>
    <nd ref="169430915"/>
    <nd ref="169430918"/>
    <nd ref="169430920"/>
    <nd ref="169430923"/>
    <nd ref="169430926"/>
    <nd ref="169430928"/>
    <nd ref="169430933"/>
    <nd ref="169430937"/>
    <nd ref="169430941"/>
    <nd ref="169430945"/>
    <nd ref="169430949"/>
    <nd ref="169430951"/>
    <nd ref="169430959"/>
    <nd ref="169430963"/>
    <nd ref="169430966"/>
    <nd ref="169430969"/>
    <nd ref="169276845"/>
    <nd ref="169430975"/>
    <nd ref="169430983"/>
    <nd ref="169430987"/>
    <nd ref="169430989"/>
    <nd ref="169430992"/>
    <nd ref="169430993"/>
    <nd ref="169430994"/>
    <nd ref="169430999"/>
    <nd ref="169431002"/>
    <nd ref="169431004"/>
    <nd ref="169431007"/>
    <nd ref="169431008"/>
    <nd ref="169431009"/>
    <nd ref="169431011"/>
    <nd ref="169431013"/>
    <nd ref="169431016"/>
    <nd ref="169431019"/>
    <nd ref="169431022"/>
    <nd ref="169431024"/>
    <nd ref="169431026"/>
    <nd ref="169431029"/>
    <nd ref="169431031"/>
    <nd ref="169431035"/>
    <nd ref="169431037"/>
    <nd ref="169431038"/>
    <nd ref="169431040"/>
    <nd ref="169431042"/>
    <nd ref="169431045"/>
    <nd ref="169431050"/>
    <nd ref="169431053"/>
    <nd ref="169431055"/>
    <nd ref="169431059"/>
    <nd ref="169431062"/>
    <nd ref="169431063"/>
    <nd ref="169431065"/>
    <nd ref="169431067"/>
    <nd ref="169431070"/>
    <nd ref="169431073"/>
    <nd ref="169431075"/>
    <nd ref="169431078"/>
    <nd ref="169431081"/>
    <nd ref="169431085"/>
    <nd ref="169431089"/>
    <nd ref="169431091"/>
    <nd ref="169431095"/>
    <nd ref="169431098"/>
    <nd ref="169431101"/>
    <nd ref="169431103"/>
    <nd ref="169431105"/>
    <nd ref="169431108"/>
    <nd ref="169431110"/>
    <nd ref="169431112"/>
    <nd ref="169431115"/>
    <nd ref="169431117"/>
    <nd ref="169431119"/>
    <nd ref="169431123"/>
    <nd ref="169431126"/>
    <nd ref="169431127"/>
    <nd ref="169431129"/>
    <nd ref="169431132"/>
    <nd ref="169431134"/>
    <nd ref="169431136"/>
    <nd ref="169431139"/>
    <nd ref="169431140"/>
    <nd ref="169431142"/>
    <nd ref="169431144"/>
    <nd ref="169431147"/>
    <nd ref="169431150"/>
    <nd ref="169431151"/>
    <nd ref="169276800"/>
    <nd ref="169431153"/>
    <nd ref="169431155"/>
    <nd ref="169431157"/>
    <nd ref="169301920"/>
    <nd ref="169431159"/>
    <nd ref="169431160"/>
    <nd ref="169431162"/>
    <nd ref="169431164"/>
    <nd ref="169431167"/>
    <nd ref="169431171"/>
    <nd ref="169431173"/>
    <nd ref="169431177"/>
    <tag k="highway" v="residential"/>
    <tag k="name" v="Hudler Town Road"/>
    <tag k="name_1" v="State Road 1568"/>
    <tag k="tiger:cfcc" v="A41"/>
    <tag k="tiger:county" v="Ashe, NC"/>
    <tag k="tiger:name_base" v="Hudler Town Road"/>
    <tag k="tiger:name_base_1" v="State Road 1568"/>
    <tag k="tiger:reviewed" v="no"/>
    <tag k="tiger:separated" v="no"/>
    <tag k="tiger:source" v="tiger_import_dch_v0.6_20070829"/>
    <tag k="tiger:tlid" v="154041752:154041755:154041376:154055226:154055227"/>
    <tag k="tiger:upload_uuid" v="bulk_upload.pl-f5d30e1e-b9c9-4043-8bc2-575d31645af6"/>
    <tag k="tiger:zip_left" v="28617"/>
    <tag k="tiger:zip_right" v="28617"/>
  </way>

</osm>
