<?xml version="1.0" encoding="UTF-8"?>
<osm version="0.6" generator="Overpass API">
<note>The data included in this document is from www.openstreetmap.org. The data is made available under ODbL.</note>
<meta osm_base="2014-09-21T23:44:02Z"/>

  <way id="16430349">
    <nd ref="169586705"/>
    <nd ref="1144895571"/>
    <nd ref="1144895568"/>
    <nd ref="169586710"/>
    <nd ref="1144895560"/>
    <nd ref="1144895551"/>
    <nd ref="1136925060"/>
    <nd ref="1144895531"/>
    <nd ref="1144895526"/>
    <nd ref="169586711"/>
    <nd ref="1136923727"/>
    <nd ref="1144895542"/>
    <nd ref="169586712"/>
    <nd ref="169586713"/>
    <nd ref="169586716"/>
    <tag k="highway" v="residential"/>
    <tag k="name" v="Cary Lane"/>
    <tag k="tiger:cfcc" v="A41"/>
    <tag k="tiger:county" v="Buncombe, NC"/>
    <tag k="tiger:name_base" v="Cary"/>
    <tag k="tiger:name_type" v="Ln"/>
    <tag k="tiger:reviewed" v="no"/>
  </way>
  <way id="16443163">
    <nd ref="169647372"/>
    <nd ref="1144895514"/>
    <nd ref="1144895513"/>
    <nd ref="1144895488"/>
    <nd ref="169705304"/>
    <nd ref="1144895504"/>
    <nd ref="169705306"/>
    <nd ref="169705309"/>
    <nd ref="1144895509"/>
    <nd ref="1144895528"/>
    <nd ref="1144895512"/>
    <nd ref="169705312"/>
    <nd ref="1136925538"/>
    <nd ref="169705313"/>
    <nd ref="1144895573"/>
    <nd ref="1144895533"/>
    <nd ref="1136926895"/>
    <nd ref="169705315"/>
    <nd ref="169705318"/>
    <nd ref="1144895564"/>
    <nd ref="169705321"/>
    <nd ref="1144895547"/>
    <nd ref="1144895516"/>
    <nd ref="169705324"/>
    <nd ref="169705326"/>
    <tag k="highway" v="residential"/>
    <tag k="name" v="Big Level Drive"/>
    <tag k="tiger:cfcc" v="A41"/>
    <tag k="tiger:county" v="Buncombe, NC"/>
    <tag k="tiger:name_base" v="Big Level"/>
    <tag k="tiger:name_type" v="Dr"/>
    <tag k="tiger:reviewed" v="no"/>
  </way>
  <way id="16450108">
    <nd ref="169647441"/>
    <nd ref="169767904"/>
    <nd ref="1840449889"/>
    <nd ref="1840449797"/>
    <nd ref="1840449928"/>
    <nd ref="1840449798"/>
    <nd ref="1840449882"/>
    <nd ref="1840449992"/>
    <nd ref="1840449937"/>
    <nd ref="1840449975"/>
    <nd ref="169767905"/>
    <nd ref="169767907"/>
    <nd ref="169767910"/>
    <nd ref="169767913"/>
    <nd ref="169767916"/>
    <nd ref="169767919"/>
    <nd ref="169767922"/>
    <nd ref="169767924"/>
    <nd ref="169767926"/>
    <nd ref="169767928"/>
    <nd ref="169767930"/>
    <nd ref="169767933"/>
    <nd ref="169767936"/>
    <nd ref="169767939"/>
    <nd ref="169767942"/>
    <nd ref="169767944"/>
    <nd ref="169767946"/>
    <nd ref="169767949"/>
    <nd ref="169767952"/>
    <tag k="highway" v="residential"/>
    <tag k="name" v="Peach Knob Drive"/>
    <tag k="tiger:cfcc" v="A41"/>
    <tag k="tiger:county" v="Buncombe, NC"/>
    <tag k="tiger:name_base" v="Peach Knob"/>
    <tag k="tiger:name_type" v="Dr"/>
    <tag k="tiger:reviewed" v="no"/>
    <tag k="tiger:zip_left" v="28804"/>
  </way>
  <way id="16451487">
    <nd ref="169705312"/>
    <nd ref="1136926417"/>
    <nd ref="1144895492"/>
    <nd ref="1144895555"/>
    <nd ref="169586705"/>
    <nd ref="169780346"/>
    <nd ref="169780347"/>
    <nd ref="169780349"/>
    <nd ref="169780352"/>
    <nd ref="169780355"/>
    <tag k="highway" v="residential"/>
    <tag k="name" v="Trail Ridge Road"/>
    <tag k="tiger:cfcc" v="A41"/>
    <tag k="tiger:county" v="Buncombe, NC"/>
    <tag k="tiger:name_base" v="Trail Ridge"/>
    <tag k="tiger:name_type" v="Rd"/>
    <tag k="tiger:reviewed" v="no"/>
  </way>
  <way id="16451489">
    <nd ref="169767905"/>
    <nd ref="169780367"/>
    <nd ref="169780370"/>
    <nd ref="169780373"/>
    <nd ref="169780376"/>
    <nd ref="169780379"/>
    <nd ref="169780382"/>
    <nd ref="169780385"/>
    <nd ref="169780389"/>
    <nd ref="169780391"/>
    <nd ref="169780393"/>
    <nd ref="169780395"/>
    <tag k="highway" v="residential"/>
    <tag k="name" v="Trail Ridge Road"/>
    <tag k="tiger:cfcc" v="A41"/>
    <tag k="tiger:county" v="Buncombe, NC"/>
    <tag k="tiger:name_base" v="Trail Ridge"/>
    <tag k="tiger:name_type" v="Rd"/>
    <tag k="tiger:reviewed" v="no"/>
  </way>
  <way id="16453609">
    <nd ref="169705315"/>
    <nd ref="1144895508"/>
    <nd ref="169799534"/>
    <nd ref="1136925586"/>
    <nd ref="1136929399"/>
    <nd ref="1136927320"/>
    <nd ref="1136925986"/>
    <nd ref="1136924610"/>
    <nd ref="1136927884"/>
    <nd ref="1136926323"/>
    <nd ref="1136924973"/>
    <nd ref="1136923645"/>
    <nd ref="1136926697"/>
    <nd ref="1136925362"/>
    <nd ref="1136924018"/>
    <nd ref="1136922618"/>
    <nd ref="1144895534"/>
    <nd ref="1144895572"/>
    <nd ref="1136927183"/>
    <nd ref="1136925841"/>
    <nd ref="1136924468"/>
    <nd ref="1144895566"/>
    <nd ref="1136923106"/>
    <nd ref="1144895552"/>
    <nd ref="1136926192"/>
    <nd ref="1144895535"/>
    <nd ref="1136924848"/>
    <nd ref="1136923495"/>
    <nd ref="1136929258"/>
    <tag k="highway" v="residential"/>
    <tag k="name" v="Abingdon Way"/>
    <tag k="tiger:cfcc" v="A41"/>
    <tag k="tiger:county" v="Buncombe, NC"/>
    <tag k="tiger:name_base" v="Abingdon"/>
    <tag k="tiger:name_type" v="Way"/>
    <tag k="tiger:reviewed" v="no"/>
    <tag k="tiger:separated" v="no"/>
    <tag k="tiger:source" v="tiger_import_dch_v0.6_20070829"/>
    <tag k="tiger:tlid" v="36915041:36899192"/>
    <tag k="tiger:upload_uuid" v="bulk_upload.pl-8ce0f50b-a930-4e72-a7fc-6d619c0c0951"/>
    <tag k="tiger:zip_left" v="28804"/>
    <tag k="tiger:zip_right" v="28804"/>
  </way>
  <way id="98261157">
    <nd ref="169594005"/>
    <nd ref="1136927155"/>
    <nd ref="1136925797"/>
    <nd ref="1136924423"/>
    <nd ref="1136923076"/>
    <nd ref="1136926158"/>
    <nd ref="1136924810"/>
    <nd ref="1136923462"/>
    <nd ref="1136929211"/>
    <nd ref="1136925182"/>
    <nd ref="1136923848"/>
    <nd ref="1136922405"/>
    <nd ref="1136927595"/>
    <nd ref="1136924206"/>
    <nd ref="1136922794"/>
    <nd ref="1136928244"/>
    <nd ref="1136926529"/>
    <nd ref="1136924667"/>
    <nd ref="1136923320"/>
    <nd ref="1136929063"/>
    <nd ref="1136926990"/>
    <nd ref="1136923706"/>
    <nd ref="1136929440"/>
    <nd ref="1136927375"/>
    <nd ref="1136926022"/>
    <nd ref="1136922656"/>
    <nd ref="1136927985"/>
    <nd ref="1136926387"/>
    <nd ref="1136925031"/>
    <nd ref="1136928648"/>
    <nd ref="1136926757"/>
    <nd ref="1136925394"/>
    <nd ref="1136924077"/>
    <nd ref="1136922769"/>
    <nd ref="1136928195"/>
    <nd ref="1136926489"/>
    <nd ref="1136925139"/>
    <nd ref="1136928931"/>
    <nd ref="1136926861"/>
    <nd ref="1136925512"/>
    <nd ref="1136924169"/>
    <nd ref="1136927257"/>
    <nd ref="1136925902"/>
    <nd ref="1136924541"/>
    <nd ref="1136923197"/>
    <nd ref="1136926276"/>
    <nd ref="1136924929"/>
    <nd ref="1136923585"/>
    <nd ref="1136929322"/>
    <nd ref="1136926719"/>
    <nd ref="1136925373"/>
    <nd ref="1136924037"/>
    <nd ref="1136922629"/>
    <nd ref="1136925737"/>
    <nd ref="1136924403"/>
    <nd ref="1136923049"/>
    <nd ref="1136928571"/>
    <nd ref="1136924791"/>
    <nd ref="1136923428"/>
    <nd ref="1136929181"/>
    <nd ref="1136927113"/>
    <nd ref="1136923826"/>
    <nd ref="1136922382"/>
    <nd ref="1136927519"/>
    <nd ref="1136926141"/>
    <nd ref="1136924265"/>
    <nd ref="1136922886"/>
    <nd ref="1136928328"/>
    <nd ref="1136926571"/>
    <nd ref="1136923283"/>
    <nd ref="1136929027"/>
    <nd ref="1136926947"/>
    <nd ref="1136925606"/>
    <nd ref="1136929410"/>
    <nd ref="1136927336"/>
    <nd ref="1136926000"/>
    <nd ref="1136924635"/>
    <nd ref="1136927930"/>
    <nd ref="1136926346"/>
    <nd ref="1136924992"/>
    <nd ref="1136923667"/>
    <nd ref="1136928745"/>
    <nd ref="1136926810"/>
    <nd ref="1136925453"/>
    <nd ref="1136924122"/>
    <nd ref="1136927195"/>
    <nd ref="1136925862"/>
    <nd ref="1136924490"/>
    <nd ref="1136923125"/>
    <nd ref="1136926212"/>
    <nd ref="1136924871"/>
    <nd ref="1136923515"/>
    <nd ref="1136929272"/>
    <nd ref="1136925228"/>
    <nd ref="1136923902"/>
    <nd ref="1136922471"/>
    <nd ref="1136927669"/>
    <nd ref="1136925061"/>
    <nd ref="1136923728"/>
    <nd ref="1136929505"/>
    <nd ref="1136927412"/>
    <nd ref="1136924109"/>
    <nd ref="1136922690"/>
    <nd ref="1136928045"/>
    <nd ref="1136926418"/>
    <nd ref="1136923097"/>
    <nd ref="1136928698"/>
    <nd ref="1136926790"/>
    <nd ref="1136925429"/>
    <nd ref="1136929247"/>
    <nd ref="1136927179"/>
    <nd ref="1136925835"/>
    <nd ref="1136924458"/>
    <nd ref="1136922529"/>
    <nd ref="1136927791"/>
    <nd ref="1136926279"/>
    <nd ref="1136924933"/>
    <nd ref="1136928449"/>
    <nd ref="1136926642"/>
    <nd ref="1136925306"/>
    <nd ref="1136923972"/>
    <nd ref="1136927040"/>
    <nd ref="1136925657"/>
    <nd ref="1136924324"/>
    <nd ref="1136922959"/>
    <nd ref="1136926056"/>
    <nd ref="1136924693"/>
    <nd ref="1136923344"/>
    <nd ref="1136929106"/>
    <nd ref="1136926497"/>
    <nd ref="1136925150"/>
    <nd ref="1136923832"/>
    <nd ref="1136922389"/>
    <nd ref="1136925515"/>
    <nd ref="1136924173"/>
    <nd ref="1136922773"/>
    <nd ref="1136928203"/>
    <nd ref="1136924545"/>
    <nd ref="1136923202"/>
    <nd ref="1136928937"/>
    <nd ref="1136926869"/>
    <nd ref="1136923589"/>
    <nd ref="1136929326"/>
    <nd ref="1136927263"/>
    <nd ref="1136925907"/>
    <nd ref="1136924043"/>
    <nd ref="1136922633"/>
    <nd ref="1136927942"/>
    <nd ref="1136926361"/>
    <nd ref="1136923061"/>
    <nd ref="1136928588"/>
    <nd ref="1136926726"/>
    <nd ref="1136925378"/>
    <nd ref="1136929185"/>
    <nd ref="1136927118"/>
    <nd ref="1136925744"/>
    <nd ref="1136924407"/>
    <nd ref="1136927537"/>
    <nd ref="1136926145"/>
    <nd ref="1136924796"/>
    <nd ref="1136923431"/>
    <nd ref="1136929293"/>
    <nd ref="1136927232"/>
    <nd ref="1136925882"/>
    <nd ref="1136924525"/>
    <nd ref="1136927729"/>
    <nd ref="1136926246"/>
    <nd ref="1136924912"/>
    <nd ref="1136923555"/>
    <nd ref="1136926609"/>
    <nd ref="1136925268"/>
    <nd ref="1136923942"/>
    <nd ref="1136922508"/>
    <nd ref="1136925636"/>
    <nd ref="1136924295"/>
    <nd ref="1136922939"/>
    <nd ref="1136928389"/>
    <nd ref="1136926115"/>
    <nd ref="1136924760"/>
    <nd ref="1136923404"/>
    <nd ref="1136929157"/>
    <nd ref="1136925116"/>
    <nd ref="1136923793"/>
    <nd ref="1136922354"/>
    <nd ref="1136927478"/>
    <nd ref="169594187"/>
    <nd ref="1136922751"/>
    <nd ref="477453730"/>
    <nd ref="1136926461"/>
    <nd ref="1136923168"/>
    <nd ref="1136928798"/>
    <nd ref="1136926829"/>
    <nd ref="1136925496"/>
    <nd ref="1136923635"/>
    <nd ref="1136929395"/>
    <nd ref="1136927316"/>
    <nd ref="1136925973"/>
    <nd ref="1136922608"/>
    <nd ref="1136927878"/>
    <nd ref="1136926318"/>
    <nd ref="1136924969"/>
    <nd ref="1136928550"/>
    <nd ref="1136926693"/>
    <nd ref="1136925358"/>
    <nd ref="1136924012"/>
    <nd ref="1136927089"/>
    <nd ref="1136925715"/>
    <nd ref="1136924386"/>
    <nd ref="1136923023"/>
    <nd ref="1136927630"/>
    <nd ref="1136926182"/>
    <nd ref="1136924840"/>
    <nd ref="1136923484"/>
    <nd ref="1136926558"/>
    <nd ref="1136925213"/>
    <nd ref="1136923874"/>
    <nd ref="1136922444"/>
    <nd ref="715494953"/>
    <nd ref="1136924249"/>
    <nd ref="1136922831"/>
    <nd ref="1136928300"/>
    <nd ref="1136924604"/>
    <nd ref="1136923258"/>
    <nd ref="1136929012"/>
    <nd ref="1136926933"/>
    <nd ref="1136924434"/>
    <nd ref="1136923080"/>
    <nd ref="1136928657"/>
    <nd ref="1136926763"/>
    <nd ref="1136923468"/>
    <nd ref="1136929217"/>
    <nd ref="1136927162"/>
    <nd ref="1136925804"/>
    <nd ref="1136922414"/>
    <nd ref="1136927599"/>
    <nd ref="1136926164"/>
    <nd ref="1136924815"/>
    <nd ref="1136928253"/>
    <nd ref="1136926540"/>
    <nd ref="1136925189"/>
    <nd ref="1136923853"/>
    <nd ref="1136929078"/>
    <nd ref="1136927001"/>
    <nd ref="1136925641"/>
    <nd ref="1136924300"/>
    <nd ref="1136927385"/>
    <nd ref="1136926028"/>
    <nd ref="1136924675"/>
    <nd ref="1136923328"/>
    <nd ref="1136926398"/>
    <nd ref="1136925035"/>
    <nd ref="1136923712"/>
    <nd ref="1136929447"/>
    <nd ref="1136925398"/>
    <nd ref="1136924087"/>
    <nd ref="1136922662"/>
    <nd ref="1136927991"/>
    <nd ref="1136925887"/>
    <nd ref="1136924529"/>
    <nd ref="1136923177"/>
    <nd ref="1136928812"/>
    <nd ref="1136924917"/>
    <nd ref="1136923561"/>
    <nd ref="1136929297"/>
    <nd ref="1136927238"/>
    <nd ref="1136923948"/>
    <nd ref="1136922513"/>
    <nd ref="1136927736"/>
    <nd ref="1136926250"/>
    <nd ref="1136922943"/>
    <nd ref="1123543066"/>
    <nd ref="1136928393"/>
    <nd ref="1136926614"/>
    <nd ref="1136925277"/>
    <nd ref="1136923414"/>
    <nd ref="1136929161"/>
    <nd ref="1136927096"/>
    <nd ref="1136925721"/>
    <nd ref="1136922362"/>
    <nd ref="1136927494"/>
    <nd ref="1136926121"/>
    <nd ref="1136924767"/>
    <nd ref="1136928143"/>
    <nd ref="1136926467"/>
    <nd ref="1136925122"/>
    <nd ref="1136923803"/>
    <nd ref="1136926837"/>
    <nd ref="1136925502"/>
    <nd ref="1136924150"/>
    <nd ref="1136922756"/>
    <nd ref="1136928336"/>
    <nd ref="1136926577"/>
    <nd ref="1136925233"/>
    <nd ref="1136923918"/>
    <nd ref="1136926962"/>
    <nd ref="1136925620"/>
    <nd ref="1136924269"/>
    <nd ref="1136922895"/>
    <nd ref="1136926005"/>
    <nd ref="1136924640"/>
    <nd ref="1136923290"/>
    <nd ref="1136929033"/>
    <nd ref="1136925000"/>
    <nd ref="1136923679"/>
    <nd ref="1136929415"/>
    <nd ref="1136927342"/>
    <nd ref="1136925466"/>
    <nd ref="1136924128"/>
    <nd ref="1136922725"/>
    <nd ref="1136928100"/>
    <nd ref="1136924503"/>
    <nd ref="1136923136"/>
    <nd ref="1136928758"/>
    <nd ref="1136926814"/>
    <nd ref="1136923523"/>
    <nd ref="1136929277"/>
    <nd ref="1136927202"/>
    <nd ref="1136925868"/>
    <nd ref="702030974"/>
    <nd ref="1136927690"/>
    <nd ref="1136926222"/>
    <nd ref="1136924879"/>
    <nd ref="1136923000"/>
    <nd ref="1136928506"/>
    <nd ref="1136926677"/>
    <nd ref="1136925337"/>
    <nd ref="1136929140"/>
    <nd ref="1136927061"/>
    <nd ref="1136925683"/>
    <nd ref="1136924363"/>
    <nd ref="1136927450"/>
    <nd ref="1136926091"/>
    <nd ref="1136924734"/>
    <nd ref="1136923371"/>
    <nd ref="1136926437"/>
    <nd ref="1136925093"/>
    <nd ref="1136923767"/>
    <nd ref="1136929554"/>
    <nd ref="1136926906"/>
    <nd ref="1136925549"/>
    <nd ref="1136924216"/>
    <nd ref="1136922801"/>
    <nd ref="1136925950"/>
    <nd ref="1136924577"/>
    <nd ref="1136923230"/>
    <nd ref="1136928991"/>
    <nd ref="1136924953"/>
    <nd ref="1136923613"/>
    <nd ref="1136929361"/>
    <nd ref="1136927299"/>
    <nd ref="1136923989"/>
    <nd ref="1136922577"/>
    <nd ref="1136927850"/>
    <nd ref="1136926298"/>
    <nd ref="1136922390"/>
    <nd ref="1136927539"/>
    <nd ref="1136926146"/>
    <nd ref="1136924797"/>
    <nd ref="1136928205"/>
    <nd ref="1136926506"/>
    <nd ref="1136925151"/>
    <nd ref="1136923833"/>
    <nd ref="1136926870"/>
    <nd ref="1136925521"/>
    <nd ref="1136924175"/>
    <nd ref="1136922774"/>
    <nd ref="1635390932"/>
    <nd ref="1136925908"/>
    <nd ref="1136924546"/>
    <nd ref="1136923203"/>
    <nd ref="1136928938"/>
    <nd ref="1136926366"/>
    <nd ref="1635390939"/>
    <nd ref="1136925002"/>
    <nd ref="1136923681"/>
    <nd ref="1635390950"/>
    <nd ref="1136929416"/>
    <nd ref="1136925379"/>
    <nd ref="1136924045"/>
    <nd ref="1136922634"/>
    <nd ref="1136927945"/>
    <nd ref="1635390956"/>
    <nd ref="1136924408"/>
    <nd ref="1136923062"/>
    <nd ref="1136928590"/>
    <nd ref="1136926728"/>
    <nd ref="1136923441"/>
    <nd ref="1136929186"/>
    <nd ref="1136927128"/>
    <nd ref="1136925745"/>
    <nd ref="1136923920"/>
    <nd ref="1136922483"/>
    <nd ref="1136927692"/>
    <nd ref="1136926224"/>
    <nd ref="1136922898"/>
    <nd ref="1136928338"/>
    <nd ref="1136926578"/>
    <nd ref="1136925234"/>
    <nd ref="1136929036"/>
    <nd ref="1136926964"/>
    <nd ref="1136925621"/>
    <nd ref="1136924270"/>
    <nd ref="702030979"/>
    <tag k="attribution" v="hikewnc.info"/>
    <tag k="bicycle" v="no"/>
    <tag k="foot" v="designated"/>
    <tag k="highway" v="path"/>
    <tag k="sac_scale" v="mountain_hiking"/>
  </way>
  <way id="173202105">
    <nd ref="169767952"/>
    <nd ref="169767955"/>
    <nd ref="169767957"/>
    <nd ref="169767960"/>
    <nd ref="169767963"/>
    <nd ref="169767966"/>
    <nd ref="169767969"/>
    <nd ref="169767972"/>
    <nd ref="169767974"/>
    <nd ref="169767976"/>
    <nd ref="169767979"/>
    <nd ref="169767984"/>
    <nd ref="169767986"/>
    <nd ref="169767989"/>
    <nd ref="169767993"/>
    <nd ref="169767996"/>
    <nd ref="1840469434"/>
    <nd ref="1840469431"/>
    <nd ref="1840469432"/>
    <nd ref="1840469435"/>
    <nd ref="169767952"/>
    <tag k="highway" v="residential"/>
    <tag k="name" v="Peach Knob Drive"/>
    <tag k="tiger:cfcc" v="A41"/>
    <tag k="tiger:county" v="Buncombe, NC"/>
    <tag k="tiger:name_base" v="Peach Knob"/>
    <tag k="tiger:name_type" v="Dr"/>
    <tag k="tiger:reviewed" v="no"/>
    <tag k="tiger:zip_left" v="28804"/>
  </way>
  <way id="286467786">
    <nd ref="169647332"/>
    <nd ref="169647334"/>
    <nd ref="1144895550"/>
    <nd ref="1144895524"/>
    <nd ref="169647336"/>
    <nd ref="169647338"/>
    <nd ref="2901451704"/>
    <nd ref="2901451705"/>
    <nd ref="1144895532"/>
    <nd ref="169647340"/>
    <nd ref="169647342"/>
    <nd ref="169647344"/>
    <nd ref="169647346"/>
    <nd ref="169647348"/>
    <nd ref="1136928306"/>
    <nd ref="1144895506"/>
    <nd ref="169647350"/>
    <nd ref="1136922844"/>
    <nd ref="1144895544"/>
    <nd ref="1136924254"/>
    <nd ref="1144895495"/>
    <nd ref="1136927642"/>
    <nd ref="169647352"/>
    <nd ref="1144895553"/>
    <nd ref="1144895491"/>
    <nd ref="169647354"/>
    <nd ref="169647357"/>
    <nd ref="169647360"/>
    <nd ref="169647364"/>
    <nd ref="169647367"/>
    <nd ref="169647369"/>
    <nd ref="1144895494"/>
    <nd ref="1136923884"/>
    <nd ref="1144895490"/>
    <nd ref="1136922452"/>
    <nd ref="169647372"/>
    <nd ref="169647375"/>
    <nd ref="1136929011"/>
    <nd ref="169647382"/>
    <nd ref="1136923256"/>
    <nd ref="169647385"/>
    <nd ref="169647388"/>
    <nd ref="169647391"/>
    <nd ref="1136924602"/>
    <nd ref="169647395"/>
    <nd ref="169647400"/>
    <nd ref="1136925971"/>
    <nd ref="169647403"/>
    <nd ref="169647406"/>
    <nd ref="169647408"/>
    <nd ref="169647410"/>
    <nd ref="169647413"/>
    <nd ref="169647415"/>
    <nd ref="1840469433"/>
    <nd ref="169647418"/>
    <nd ref="1840449978"/>
    <nd ref="1840449716"/>
    <nd ref="1840449964"/>
    <nd ref="1840449789"/>
    <nd ref="169647420"/>
    <nd ref="169647422"/>
    <nd ref="169647424"/>
    <nd ref="1840450003"/>
    <nd ref="169647426"/>
    <nd ref="169647428"/>
    <nd ref="169647431"/>
    <nd ref="169647433"/>
    <nd ref="169647435"/>
    <nd ref="1840449914"/>
    <nd ref="169647437"/>
    <nd ref="169647439"/>
    <nd ref="169647441"/>
    <nd ref="169647448"/>
    <nd ref="1840449720"/>
    <nd ref="1840449963"/>
    <nd ref="1840449800"/>
    <nd ref="1840450042"/>
    <nd ref="1840449816"/>
    <nd ref="1840449885"/>
    <nd ref="1840450050"/>
    <nd ref="169647451"/>
    <nd ref="1840449795"/>
    <nd ref="169647452"/>
    <nd ref="1840449966"/>
    <nd ref="169631179"/>
    <nd ref="169647454"/>
    <nd ref="1840449823"/>
    <nd ref="1840449835"/>
    <nd ref="1840449831"/>
    <nd ref="1840449968"/>
    <nd ref="1840449919"/>
    <nd ref="169647457"/>
    <nd ref="169647459"/>
    <nd ref="169647461"/>
    <nd ref="169647463"/>
    <nd ref="169647465"/>
    <nd ref="169647467"/>
    <nd ref="1840449981"/>
    <nd ref="1840449808"/>
    <nd ref="1840449999"/>
    <nd ref="1840449984"/>
    <nd ref="169647469"/>
    <nd ref="1840449839"/>
    <nd ref="1840450046"/>
    <nd ref="1840449995"/>
    <nd ref="169647471"/>
    <nd ref="1840449923"/>
    <nd ref="169647473"/>
    <nd ref="1840449961"/>
    <nd ref="1840449844"/>
    <nd ref="169647475"/>
    <nd ref="169647477"/>
    <nd ref="169647479"/>
    <nd ref="169647481"/>
    <nd ref="169647484"/>
    <nd ref="169647486"/>
    <nd ref="169647488"/>
    <nd ref="1840450016"/>
    <nd ref="1840449905"/>
    <nd ref="1840449804"/>
    <nd ref="1840450043"/>
    <nd ref="169647490"/>
    <nd ref="169647492"/>
    <nd ref="169647494"/>
    <nd ref="169647496"/>
    <nd ref="169647498"/>
    <nd ref="169647500"/>
    <nd ref="169647502"/>
    <nd ref="1840449887"/>
    <nd ref="1840450041"/>
    <nd ref="1840450020"/>
    <nd ref="1840449786"/>
    <nd ref="1840449909"/>
    <nd ref="1840449718"/>
    <nd ref="169647503"/>
    <nd ref="169647505"/>
    <nd ref="1840449820"/>
    <nd ref="2901380868"/>
    <nd ref="2901380862"/>
    <nd ref="2901380867"/>
    <nd ref="169647507"/>
    <nd ref="2901380869"/>
    <nd ref="2901380865"/>
    <nd ref="2901380863"/>
    <nd ref="1840450044"/>
    <nd ref="2901380866"/>
    <nd ref="2901380864"/>
    <nd ref="1840449895"/>
    <nd ref="169647509"/>
    <nd ref="3028885122"/>
    <nd ref="169647511"/>
    <nd ref="1840450048"/>
    <nd ref="169647513"/>
    <nd ref="3028885121"/>
    <nd ref="1840449884"/>
    <nd ref="3028885120"/>
    <nd ref="1840449827"/>
    <nd ref="1840449897"/>
    <nd ref="3028885123"/>
    <nd ref="3028885119"/>
    <nd ref="1840450011"/>
    <nd ref="1840450052"/>
    <nd ref="169647515"/>
    <nd ref="3028885118"/>
    <nd ref="1840449793"/>
    <nd ref="1840449723"/>
    <nd ref="3028885124"/>
    <nd ref="1840449988"/>
    <nd ref="3028885117"/>
    <nd ref="1840449972"/>
    <nd ref="1840449893"/>
    <nd ref="3028885125"/>
    <nd ref="1840449791"/>
    <nd ref="3028885116"/>
    <nd ref="169647516"/>
    <nd ref="1840449891"/>
    <nd ref="1840449970"/>
    <nd ref="1840449940"/>
    <nd ref="1840449812"/>
    <nd ref="3028885115"/>
    <nd ref="1840449901"/>
    <nd ref="3028885114"/>
    <nd ref="169647518"/>
    <nd ref="169647520"/>
    <nd ref="169647522"/>
    <nd ref="169647524"/>
    <nd ref="169647526"/>
    <nd ref="169647529"/>
    <nd ref="1840450006"/>
    <nd ref="2835797033"/>
    <nd ref="169647532"/>
    <nd ref="2835797034"/>
    <nd ref="169512142"/>
    <nd ref="169647534"/>
    <nd ref="2835797035"/>
    <nd ref="169647536"/>
    <nd ref="169647540"/>
    <nd ref="169647543"/>
    <nd ref="169647546"/>
    <nd ref="169502721"/>
    <nd ref="169647550"/>
    <nd ref="169647552"/>
    <nd ref="169647554"/>
    <nd ref="480530961"/>
    <nd ref="480530956"/>
    <nd ref="480530958"/>
    <nd ref="480530960"/>
    <nd ref="169647556"/>
    <nd ref="480530954"/>
    <nd ref="480530953"/>
    <nd ref="480530949"/>
    <nd ref="480530950"/>
    <nd ref="480530951"/>
    <nd ref="169647558"/>
    <nd ref="480530947"/>
    <nd ref="480530964"/>
    <nd ref="480530963"/>
    <nd ref="480530966"/>
    <nd ref="169647560"/>
    <nd ref="480530967"/>
    <nd ref="480530969"/>
    <nd ref="480530970"/>
    <nd ref="480530973"/>
    <nd ref="169647562"/>
    <nd ref="480530974"/>
    <nd ref="480530977"/>
    <nd ref="480530976"/>
    <nd ref="169597457"/>
    <nd ref="480530984"/>
    <nd ref="480530983"/>
    <nd ref="480530980"/>
    <nd ref="480530979"/>
    <nd ref="480530985"/>
    <nd ref="480530987"/>
    <nd ref="169647563"/>
    <nd ref="169647564"/>
    <nd ref="169647565"/>
    <nd ref="480530988"/>
    <nd ref="480530990"/>
    <nd ref="169647566"/>
    <nd ref="480530994"/>
    <nd ref="480530991"/>
    <nd ref="480530993"/>
    <nd ref="169647567"/>
    <nd ref="1840439188"/>
    <nd ref="169647568"/>
    <nd ref="169647569"/>
    <nd ref="169647570"/>
    <nd ref="480530996"/>
    <nd ref="169647571"/>
    <nd ref="169647572"/>
    <nd ref="169647573"/>
    <nd ref="169647574"/>
    <nd ref="169647575"/>
    <nd ref="2820803347"/>
    <nd ref="169647576"/>
    <nd ref="169647578"/>
    <nd ref="169647579"/>
    <nd ref="169647581"/>
    <nd ref="169647583"/>
    <nd ref="2820803346"/>
    <nd ref="169647584"/>
    <nd ref="480531000"/>
    <nd ref="480530998"/>
    <nd ref="169647586"/>
    <nd ref="169647587"/>
    <nd ref="2729412424"/>
    <nd ref="2729412423"/>
    <nd ref="480531003"/>
    <nd ref="2729412422"/>
    <nd ref="2729412421"/>
    <nd ref="2729412420"/>
    <nd ref="2729412419"/>
    <nd ref="2729412418"/>
    <nd ref="169647589"/>
    <nd ref="169647591"/>
    <nd ref="169647595"/>
    <nd ref="2991095836"/>
    <nd ref="169647597"/>
    <nd ref="480531004"/>
    <nd ref="480531007"/>
    <nd ref="169647600"/>
    <nd ref="169647603"/>
    <nd ref="2991095835"/>
    <nd ref="2991095834"/>
    <nd ref="480531006"/>
    <nd ref="2991095833"/>
    <nd ref="169647604"/>
    <nd ref="2991092832"/>
    <nd ref="1840411976"/>
    <nd ref="1840411977"/>
    <nd ref="2991092831"/>
    <nd ref="2991092830"/>
    <nd ref="480531009"/>
    <nd ref="169647605"/>
    <nd ref="1840411963"/>
    <nd ref="480531011"/>
    <nd ref="1840411974"/>
    <nd ref="169647607"/>
    <nd ref="480531013"/>
    <nd ref="2470629949"/>
    <tag k="highway" v="secondary"/>
    <tag k="name" v="Town Mountain Road"/>
    <tag k="ref" v="NC 694"/>
    <tag k="tiger:cfcc" v="A31"/>
    <tag k="tiger:county" v="Buncombe, NC"/>
    <tag k="tiger:name_base" v="Town Mountain"/>
    <tag k="tiger:name_base_1" v="State Highway 694"/>
    <tag k="tiger:name_type" v="Rd"/>
    <tag k="tiger:reviewed" v="no"/>
    <tag k="tiger:zip_left" v="28804"/>
    <tag k="tiger:zip_right" v="28804"/>
  </way>
  <way id="291280540">
    <nd ref="169594005"/>
    <nd ref="2742917028"/>
    <nd ref="2742917025"/>
    <nd ref="2742917032"/>
    <nd ref="169594008"/>
    <nd ref="2742917041"/>
    <nd ref="2742917036"/>
    <nd ref="2742917044"/>
    <nd ref="169594011"/>
    <nd ref="2742917047"/>
    <nd ref="169594013"/>
    <nd ref="2742917050"/>
    <nd ref="2742917071"/>
    <nd ref="2742917057"/>
    <nd ref="2742917053"/>
    <nd ref="2742917059"/>
    <nd ref="169594014"/>
    <nd ref="169594015"/>
    <nd ref="560093872"/>
    <nd ref="2742917065"/>
    <nd ref="2742917062"/>
    <nd ref="169594016"/>
    <nd ref="169594017"/>
    <nd ref="2742917068"/>
    <nd ref="169594019"/>
    <nd ref="560093873"/>
    <nd ref="1136928195"/>
    <nd ref="169594021"/>
    <nd ref="169594022"/>
    <nd ref="560098471"/>
    <nd ref="560093874"/>
    <nd ref="169594023"/>
    <nd ref="169594025"/>
    <nd ref="169594027"/>
    <nd ref="169594030"/>
    <nd ref="169594033"/>
    <nd ref="169594037"/>
    <nd ref="169594042"/>
    <nd ref="169594044"/>
    <nd ref="169594048"/>
    <nd ref="169594050"/>
    <nd ref="169594053"/>
    <nd ref="169594056"/>
    <nd ref="169594058"/>
    <nd ref="169594060"/>
    <nd ref="169594062"/>
    <nd ref="169594064"/>
    <nd ref="169594067"/>
    <nd ref="169594071"/>
    <nd ref="169594075"/>
    <nd ref="169594077"/>
    <nd ref="169594079"/>
    <nd ref="560098644"/>
    <nd ref="560098645"/>
    <nd ref="169594081"/>
    <nd ref="169594083"/>
    <nd ref="169594086"/>
    <nd ref="560098646"/>
    <nd ref="2914616474"/>
    <nd ref="560098647"/>
    <nd ref="169594090"/>
    <nd ref="169594093"/>
    <nd ref="169594096"/>
    <nd ref="169594098"/>
    <nd ref="560099349"/>
    <nd ref="560099350"/>
    <nd ref="560099351"/>
    <nd ref="169594101"/>
    <nd ref="560099352"/>
    <nd ref="560099353"/>
    <nd ref="560099354"/>
    <nd ref="560099355"/>
    <nd ref="560099356"/>
    <nd ref="169594104"/>
    <nd ref="560099357"/>
    <nd ref="560099358"/>
    <nd ref="169594106"/>
    <nd ref="560099359"/>
    <nd ref="560099360"/>
    <nd ref="560099361"/>
    <nd ref="169594107"/>
    <nd ref="169594110"/>
    <nd ref="169594113"/>
    <nd ref="169594115"/>
    <nd ref="560099363"/>
    <nd ref="560099364"/>
    <nd ref="169594117"/>
    <nd ref="560099365"/>
    <nd ref="169594119"/>
    <nd ref="169594120"/>
    <nd ref="169594123"/>
    <nd ref="169594126"/>
    <nd ref="169594129"/>
    <nd ref="169594132"/>
    <nd ref="169594135"/>
    <nd ref="169594137"/>
    <nd ref="169594139"/>
    <nd ref="169594140"/>
    <nd ref="169594142"/>
    <nd ref="169594144"/>
    <nd ref="169594149"/>
    <nd ref="169594154"/>
    <nd ref="560099366"/>
    <nd ref="560099367"/>
    <nd ref="1136925217"/>
    <nd ref="169594156"/>
    <nd ref="169594159"/>
    <nd ref="169594162"/>
    <nd ref="169594168"/>
    <nd ref="169594169"/>
    <nd ref="169594170"/>
    <nd ref="169594172"/>
    <nd ref="169594175"/>
    <nd ref="169594177"/>
    <nd ref="169594179"/>
    <nd ref="169594181"/>
    <nd ref="169594183"/>
    <nd ref="169594185"/>
    <nd ref="169594187"/>
    <nd ref="169594189"/>
    <nd ref="169594192"/>
    <nd ref="169594194"/>
    <nd ref="169594196"/>
    <nd ref="169594198"/>
    <nd ref="169594201"/>
    <nd ref="169594205"/>
    <nd ref="169594208"/>
    <nd ref="2832705650"/>
    <nd ref="169594211"/>
    <nd ref="169594213"/>
    <nd ref="169594215"/>
    <nd ref="169594217"/>
    <nd ref="169594220"/>
    <nd ref="169594223"/>
    <nd ref="169594225"/>
    <nd ref="1136922762"/>
    <nd ref="1136922517"/>
    <nd ref="169594227"/>
    <nd ref="169594232"/>
    <nd ref="715494748"/>
    <nd ref="169594235"/>
    <nd ref="169594238"/>
    <nd ref="169594241"/>
    <nd ref="1136929169"/>
    <nd ref="169594246"/>
    <nd ref="1136927101"/>
    <nd ref="169594248"/>
    <nd ref="169594250"/>
    <nd ref="169594252"/>
    <nd ref="169594254"/>
    <nd ref="169594255"/>
    <nd ref="1136925727"/>
    <nd ref="169594256"/>
    <nd ref="169594261"/>
    <nd ref="169594263"/>
    <nd ref="169594264"/>
    <nd ref="169594266"/>
    <nd ref="169594268"/>
    <nd ref="169594270"/>
    <nd ref="1136924397"/>
    <nd ref="1136927500"/>
    <nd ref="169594271"/>
    <nd ref="169594272"/>
    <nd ref="169594273"/>
    <nd ref="1136926134"/>
    <nd ref="169594274"/>
    <nd ref="1136924771"/>
    <nd ref="169594276"/>
    <nd ref="1136923420"/>
    <nd ref="169594278"/>
    <nd ref="169594281"/>
    <nd ref="1136926478"/>
    <nd ref="169594283"/>
    <nd ref="169594285"/>
    <nd ref="1123543196"/>
    <nd ref="1123542669"/>
    <nd ref="169594288"/>
    <nd ref="169594289"/>
    <nd ref="169594291"/>
    <nd ref="1136927846"/>
    <nd ref="169594293"/>
    <nd ref="1136926297"/>
    <nd ref="169594295"/>
    <nd ref="1123542634"/>
    <nd ref="1136925058"/>
    <nd ref="1123542752"/>
    <nd ref="1123542974"/>
    <nd ref="1123542859"/>
    <nd ref="169594297"/>
    <nd ref="1123543146"/>
    <nd ref="1123543040"/>
    <nd ref="1123543294"/>
    <nd ref="169594298"/>
    <nd ref="1123543325"/>
    <nd ref="1123542902"/>
    <nd ref="1123542716"/>
    <nd ref="169594300"/>
    <nd ref="169594302"/>
    <nd ref="1123543072"/>
    <nd ref="1123542940"/>
    <nd ref="169594304"/>
    <nd ref="169594306"/>
    <nd ref="169594308"/>
    <nd ref="1136923726"/>
    <nd ref="169594311"/>
    <nd ref="169594314"/>
    <nd ref="1136929504"/>
    <nd ref="169594317"/>
    <nd ref="169594320"/>
    <nd ref="1635390928"/>
    <nd ref="1136927410"/>
    <nd ref="169594327"/>
    <nd ref="1635390936"/>
    <nd ref="1635390948"/>
    <nd ref="1635390949"/>
    <nd ref="169594330"/>
    <nd ref="1635390947"/>
    <nd ref="169594332"/>
    <nd ref="169594334"/>
    <nd ref="169594336"/>
    <nd ref="169594338"/>
    <nd ref="1635390926"/>
    <nd ref="169594341"/>
    <nd ref="702030949"/>
    <nd ref="169594344"/>
    <tag k="hgv" v="no"/>
    <tag k="highway" v="secondary"/>
    <tag k="layer" v="1"/>
    <tag k="name" v="Blue Ridge Parkway"/>
    <tag k="oneway" v="no"/>
    <tag k="rcn_ref" v="2"/>
    <tag k="ref" v="BRP"/>
    <tag k="tiger:cfcc" v="A41"/>
    <tag k="tiger:county" v="Buncombe, NC"/>
    <tag k="tiger:name_base" v="Blue Ridge"/>
    <tag k="tiger:name_type" v="Pky"/>
    <tag k="tiger:reviewed" v="no"/>
    <tag k="website" v="http://www.blueridgeparkway.org/"/>
  </way>

</osm>
